csexp.py
setup.py
csexp.egg-info/PKG-INFO
csexp.egg-info/SOURCES.txt
csexp.egg-info/dependency_links.txt
csexp.egg-info/top_level.txt