Metadata-Version: 1.1
Name: csexp
Version: 0.1
Summary: Canonical S-expression library
Home-page: https://github.com/dlitz/python-csexp
Author: Dwayne C. Litzenberger
Author-email: dlitz@dlitz.net
License: MIT
Platform: UNKNOWN
Classifier: Development Status :: 3 - Alpha
Classifier: Intended Audience :: Developers
Classifier: License :: OSI Approved :: MIT License
Classifier: Programming Language :: Python :: 2
